redesign/health/__init__.py
redesign/health/patterns.py
redesign.health-0.1.dist-info/LICENSE
redesign.health-0.1.dist-info/METADATA
redesign.health-0.1.dist-info/WHEEL
redesign.health-0.1.dist-info/top_level.txt
redesign.health-0.1.dist-info/RECORD
